ci_environment/CiEnvironments.json
ci_environment/__init__.py
ci_environment/ci_environment.py
ci_environment/variable_expression.py
cuke_ci_environment-0.1.0.dist-info/METADATA
cuke_ci_environment-0.1.0.dist-info/WHEEL
cuke_ci_environment-0.1.0.dist-info/top_level.txt
cuke_ci_environment-0.1.0.dist-info/RECORD
